Processor/processor.v
module ALU (
    input  [15:0] A,
    input  [15:0] B,
    input  [2:0]  ALU_Op,
    output reg [15:0] Result,
    output Zero
);
    always @(*) begin
        case (ALU_Op)
            3'b000: Result = A + B;       // ADD
            3'b001: Result = A - B;       // SUB
            3'b010: Result = A & B;       // AND
            3'b011: Result = A | B;       // OR
            3'b100: Result = A ^ B;       // XOR
            3'b101: Result = ~A;          // NOT
            default: Result = 16'd0;
        endcase
    end
    
    // Флаг нуля для ветвлений (BEQ)
    assign Zero = (Result == 16'd0) ? 1'b1 : 1'b0;
endmodule

module Register_File (
    input  clk,
    input  we,
    input  [2:0] read_reg1,
    input  [2:0] read_reg2,
    input  [2:0] write_reg,
    input  [15:0] write_data,
    output [15:0] read_data1,
    output [15:0] read_data2
);
    reg [15:0] regs [0:7];
    integer i;

    // Инициализация нулями
    initial begin
        for (i = 0; i < 8; i = i + 1) regs[i] = 16'd0;
    end

    // R0 всегда равен 0
    assign read_data1 = (read_reg1 == 3'b000) ? 16'd0 : regs[read_reg1];
    assign read_data2 = (read_reg2 == 3'b000) ? 16'd0 : regs[read_reg2];

    always @(posedge clk) begin
        if (we && write_reg != 3'b000) begin
            regs[write_reg] <= write_data;
        end
    end
endmodule

module Control_Unit (
    input  clk,
    input  rst,
    input  [3:0] opcode,
    
    output reg PC_Write,
    output reg IR_Write,
    output reg Reg_Write,
    output reg Mem_Write,
    output reg Mem_Read,
    output reg [1:0] ALU_Src,
    output reg [2:0] ALU_Op,
    output reg [1:0] Reg_Dst_Sel,
    output reg Branch_En,
    output reg Jump_En
);

    // Кодирование состояний автомата
    localparam FETCH      = 3'b000;
    localparam DECODE     = 3'b001;
    localparam EXECUTE    = 3'b010;
    localparam WRITEBACK  = 3'b011;

    reg [2:0] current_state, next_state;

    // 1. регистр сотсояний
    always @(posedge clk or posedge rst) begin
        if (rst) current_state <= FETCH;
        else     current_state <= next_state;
    end

    // 2. комбинационная логика переходов
    always @(*) begin
        case (current_state)
            FETCH:      next_state = DECODE;
            DECODE:     next_state = EXECUTE;
            EXECUTE:    next_state = WRITEBACK;
            WRITEBACK:  next_state = FETCH;
            default:    next_state = FETCH;
        endcase
    end

    // 3. комбинационая логика выходов
    // Управляющие сигналы расставляются в зависимости от текущего такта и декодированного opcode.
    always @(*) begin
        // Значения по умолчанию
        PC_Write = 0; IR_Write = 0; Reg_Write = 0; Mem_Write = 0; Mem_Read = 0;
        Branch_En = 0; Jump_En = 0; ALU_Src = 2'b00; ALU_Op = 3'b000; Reg_Dst_Sel = 2'b00;

        case (current_state)
            FETCH: begin
                IR_Write = 1;
            end
            
            DECODE: begin
                // Подготовка к выполнению (чтение регистров происходит асинхронно в DataPath)
            end
            
            EXECUTE: begin
                case (opcode)
                    4'b0000: ALU_Op = 3'b000; // ADD
                    4'b0001: ALU_Op = 3'b001; // SUB
                    4'b0010: ALU_Op = 3'b010; // AND
                    4'b0011: ALU_Op = 3'b011; // OR
                    4'b0100: ALU_Op = 3'b100; // XOR
                    4'b0101: ALU_Op = 3'b101; // NOT
                    4'b0110: begin ALU_Src = 2'b01; ALU_Op = 3'b000; Mem_Read = 1; end // LOAD
                    4'b0111: begin ALU_Src = 2'b01; ALU_Op = 3'b000; Mem_Write = 1; end // STORE
                    4'b1001: begin ALU_Op = 3'b001; Branch_En = 1; end // BEQ
                    4'b1000: Jump_En = 1; // JUMP
                endcase
            end
            
            WRITEBACK: begin
                PC_Write = 1; // Обновляем PC в конце цикла
                case (opcode)
                    4'b0000, 4'b0001, 4'b0010, 4'b0011, 4'b0100, 4'b0101: begin 
                        Reg_Write = 1; Reg_Dst_Sel = 2'b00; // ALU Result
                    end
                    4'b0110: begin 
                        Reg_Write = 1; Reg_Dst_Sel = 2'b01; // Mem Data
                    end
                endcase
            end
        endcase
    end
endmodule

module Top_Module (
    input clk,
    input rst
);
    // Программный счетчик (PC) и регистр инструкций (IR)
    reg [11:0] PC;
    reg [15:0] IR;

    // Память
    reg [15:0] Instr_Mem [0:1023];
    reg [15:0] Data_Mem  [0:1023];

    // Внутренние провода
    wire [15:0] instr_wire = Instr_Mem[PC];
    
    wire PC_Write, IR_Write, Reg_Write, Mem_Write, Mem_Read, Branch_En, Jump_En;
    wire [1:0] ALU_Src, Reg_Dst_Sel;
    wire [2:0] ALU_Op;
    
    wire [15:0] rd1, rd2, alu_res;
    wire alu_zero;
    
    // Распаковка инструкции (IR)
    wire [3:0]  opcode = IR[15:12];
    wire [2:0]  reg_dst = IR[11:9];
    wire [2:0]  reg_src1 = IR[8:6];
    wire [2:0]  reg_src2 = (opcode == 4'b0111) ? reg_dst : IR[5:3];
    wire [5:0]  imm6 = IR[5:0];
    wire [11:0] imm12 = IR[11:0];
    
    // Расширение знака для immediate
    wire [15:0] sign_ext_imm = {{10{imm6[5]}}, imm6};

    // Обновление IR
    always @(posedge clk) begin
        if (IR_Write) IR <= instr_wire;
    end

    Control_Unit CU (
        .clk(clk), .rst(rst), .opcode(opcode),
        .PC_Write(PC_Write), .IR_Write(IR_Write), .Reg_Write(Reg_Write),
        .Mem_Write(Mem_Write), .Mem_Read(Mem_Read), .ALU_Src(ALU_Src),
        .ALU_Op(ALU_Op), .Reg_Dst_Sel(Reg_Dst_Sel), .Branch_En(Branch_En), .Jump_En(Jump_En)
    );

    // Мультиплексор данных для записи в регистр
    wire [15:0] write_data_to_reg = (Reg_Dst_Sel == 2'b01) ? Data_Mem[alu_res[11:0]] : alu_res;

    Register_File RF (
        .clk(clk), .we(Reg_Write),
        .read_reg1(reg_src1), .read_reg2(reg_src2), .write_reg(reg_dst),
        .write_data(write_data_to_reg),
        .read_data1(rd1), .read_data2(rd2)
    );

    // Мультиплексор второго операнда АЛУ
    wire [15:0] alu_b_in = (ALU_Src == 2'b01) ? sign_ext_imm : rd2;

    ALU ALU_Inst (
        .A(rd1), .B(alu_b_in), .ALU_Op(ALU_Op),
        .Result(alu_res), .Zero(alu_zero)
    );

    // Работа с памятью данных
    always @(posedge clk) begin
        if (Mem_Write) Data_Mem[alu_res[11:0]] <= rd2; // Для store rd2 - это данные (поле Rd в инструкции)
    end

    // Логика следующего адреса (PC)
    always @(posedge clk or posedge rst) begin
        if (rst) begin
            PC <= 12'd0;
        end else if (PC_Write) begin
            if (Jump_En) 
                PC <= imm12;
            else if (Branch_En && alu_zero) 
                PC <= PC + 1 + sign_ext_imm[11:0];
            else 
                PC <= PC + 1;
        end
    end
endmodule

Processor/tb_Top_Module.v
`timescale 1ns / 1ps

module tb_Top_Module();

    // Сигналы для подключения к процессору
    reg clk;
    reg rst;

    // Экземпляр процессора (UUT - Unit Under Test)
    Top_Module uut (
        .clk(clk),
        .rst(rst)
    );

    // Генерация тактового сигнала (Clock) с периодом 10 нс (100 МГц)
    initial begin
        clk = 0;
        forever #5 clk = ~clk; 
    end

    // Основной блок симуляции
    initial begin
        // Включение записи временных диаграмм (для GTKWave)
        $dumpfile("processor_wave.vcd");
        $dumpvars(0, tb_Top_Module);

        // Инициализация памяти данных (Тестовые векторы)
        uut.Data_Mem[0] = 16'd15; // Первое слагаемое
        uut.Data_Mem[1] = 16'd25; // Второе слагаемое
        uut.Data_Mem[2] = 16'd0;  // Сюда запишем результат

        // Загрузка программы в память инструкций (Машинный код)
        uut.Instr_Mem[0] = 16'h6200; // LOAD  R1, 0(R0)
        uut.Instr_Mem[1] = 16'h6401; // LOAD  R2, 1(R0)
        uut.Instr_Mem[2] = 16'h0650; // ADD   R3, R1, R2
        uut.Instr_Mem[3] = 16'h7602; // STORE R3, 2(R0)
        uut.Instr_Mem[4] = 16'h8004; // JUMP  4

        // Аппаратный сброс (Reset)
        rst = 1;
        #15;      // Ждем 1.5 такта
        rst = 0;  // Отпускаем сброс, процессор начинает работу

        // Ждем достаточное время для выполнения 5 инструкций
        // У нас 4 такта на инструкцию: 5 * 4 * 10 нс = 200 нс
        #250;

        // Вывод результатов в консоль
        $display("      results     ");
        $display("Input:");
        $display("Data_Mem[0] = %d", uut.Data_Mem[0]);
        $display("Data_Mem[1] = %d", uut.Data_Mem[1]);
        $display("----------------------------------------");
        $display("Registers after:");
        $display("R1 = %d", uut.RF.regs[1]);
        $display("R2 = %d", uut.RF.regs[2]);
        $display("R3 = %d (sum in register)", uut.RF.regs[3]);
        $display("----------------------------------------");
        $display("memory after exec store:");
        $display("Data_Mem[2] = %d (target: 40)", uut.Data_Mem[2]);
        
        if (uut.Data_Mem[2] == 16'd40)
            $display(">>> success <<<");
        else
            $display(">>> unsucces <<<");
            
        $finish;
    end

endmodule

Processor/processor_wave.vcd
$date
	Thu May 28 01:05:08 2026
$end
$version
	Icarus Verilog
$end
$timescale
	1ps
$end
$scope module tb_Top_Module $end
$var reg 1 ! clk $end
$var reg 1 " rst $end
$scope module uut $end
$var wire 1 ! clk $end
$var wire 16 # instr_wire [15:0] $end
$var wire 1 " rst $end
$var wire 16 $ write_data_to_reg [15:0] $end
$var wire 16 % sign_ext_imm [15:0] $end
$var wire 3 & reg_src2 [2:0] $end
$var wire 3 ' reg_src1 [2:0] $end
$var wire 3 ( reg_dst [2:0] $end
$var wire 16 ) rd2 [15:0] $end
$var wire 16 * rd1 [15:0] $end
$var wire 4 + opcode [3:0] $end
$var wire 6 , imm6 [5:0] $end
$var wire 12 - imm12 [11:0] $end
$var wire 1 . alu_zero $end
$var wire 16 / alu_res [15:0] $end
$var wire 16 0 alu_b_in [15:0] $end
$var wire 1 1 Reg_Write $end
$var wire 2 2 Reg_Dst_Sel [1:0] $end
$var wire 1 3 PC_Write $end
$var wire 1 4 Mem_Write $end
$var wire 1 5 Mem_Read $end
$var wire 1 6 Jump_En $end
$var wire 1 7 IR_Write $end
$var wire 1 8 Branch_En $end
$var wire 2 9 ALU_Src [1:0] $end
$var wire 3 : ALU_Op [2:0] $end
$var reg 16 ; IR [15:0] $end
$var reg 12 < PC [11:0] $end
$scope module ALU_Inst $end
$var wire 16 = B [15:0] $end
$var wire 1 . Zero $end
$var wire 3 > ALU_Op [2:0] $end
$var wire 16 ? A [15:0] $end
$var reg 16 @ Result [15:0] $end
$upscope $end
$scope module CU $end
$var wire 1 ! clk $end
$var wire 4 A opcode [3:0] $end
$var wire 1 " rst $end
$var parameter 3 B DECODE $end
$var parameter 3 C EXECUTE $end
$var parameter 3 D FETCH $end
$var parameter 3 E WRITEBACK $end
$var reg 3 F ALU_Op [2:0] $end
$var reg 2 G ALU_Src [1:0] $end
$var reg 1 8 Branch_En $end
$var reg 1 7 IR_Write $end
$var reg 1 6 Jump_En $end
$var reg 1 5 Mem_Read $end
$var reg 1 4 Mem_Write $end
$var reg 1 3 PC_Write $end
$var reg 2 H Reg_Dst_Sel [1:0] $end
$var reg 1 1 Reg_Write $end
$var reg 3 I current_state [2:0] $end
$var reg 3 J next_state [2:0] $end
$upscope $end
$scope module RF $end
$var wire 1 ! clk $end
$var wire 3 K read_reg1 [2:0] $end
$var wire 3 L read_reg2 [2:0] $end
$var wire 1 1 we $end
$var wire 16 M write_data [15:0] $end
$var wire 3 N write_reg [2:0] $end
$var wire 16 O read_data2 [15:0] $end
$var wire 16 P read_data1 [15:0] $end
$var integer 32 Q i [31:0] $end
$upscope $end
$upscope $end
$upscope $end
$enddefinitions $end
$comment Show the parameter values. $end
$dumpall
b11 E
b0 D
b10 C
b1 B
$end
#0
$dumpvars
b1000 Q
bx P
bx O
bx N
bx M
bx L
bx K
b1 J
b0 I
b0 H
b0 G
b0 F
bx A
bx @
bx ?
b0 >
bx =
b0 <
bx ;
b0 :
b0 9
08
17
06
05
04
03
b0 2
01
bx 0
bx /
x.
bx -
bx ,
bx +
bx *
bx )
bx (
bx '
bx &
bx %
bx $
b110001000000000 #
1"
0!
$end
#5000
1.
b0 $
b0 M
b0 /
b0 @
b0 0
b0 =
b0 )
b0 O
17
b0 *
b0 ?
b0 P
b0 &
b0 L
b0 %
b110 +
b110 A
b1 (
b1 N
b0 '
b0 K
b0 ,
b1000000000 -
b110001000000000 ;
1!
#10000
0!
#15000
07
b10 J
b1 I
1!
0"
#20000
0!
#25000
15
b1 9
b1 G
b11 J
b10 I
1!
#30000
0!
#35000
b1111 $
b1111 M
b1 2
b1 H
11
13
b0 9
b0 G
05
b0 J
b11 I
1!
#40000
0!
#45000
b0 $
b0 M
17
b0 2
b0 H
01
03
b1 J
b110010000000001 #
b1 <
b0 I
1!
#50000
0!
#55000
b1 %
07
b10 J
b10 (
b10 N
b1 ,
b10000000001 -
b1 I
b110010000000001 ;
1!
#60000
0!
#65000
0.
b1 $
b1 M
b1 /
b1 @
b1 0
b1 =
15
b1 9
b1 G
b11 J
b10 I
1!
#70000
0!
#75000
1.
b0 /
b0 @
b1111 $
b1111 M
b0 0
b0 =
b1 2
b1 H
11
13
b0 9
b0 G
05
b0 J
b11 I
1!
#80000
0!
#85000
b0 $
b0 M
17
b0 2
b0 H
01
03
b1 J
b11001010000 #
b10 <
b0 I
1!
#90000
0!
#95000
0.
b11110 $
b11110 M
b1111 0
b1111 =
b11110 /
b11110 @
b1111 )
b1111 O
b1111 *
b1111 ?
b1111 P
b10 &
b10 L
b10000 %
07
b10 J
b0 +
b0 A
b11 (
b11 N
b1 '
b1 K
b10000 ,
b11001010000 -
b1 I
b11001010000 ;
1!
#100000
0!
#105000
b11 J
b10 I
1!
#110000
0!
#115000
11
13
b0 J
b11 I
1!
#120000
0!
#125000
17
01
03
b1 J
b111011000000010 #
b11 <
b0 I
1!
#130000
0!
#135000
b11110 0
b11110 =
b11110 $
b11110 M
b11110 )
b11110 O
b11110 /
b11110 @
b0 *
b0 ?
b0 P
b11 &
b11 L
b10 %
07
b10 J
b111 +
b111 A
b0 '
b0 K
b10 ,
b11000000010 -
b1 I
b111011000000010 ;
1!
#140000
0!
#145000
b10 $
b10 M
b10 /
b10 @
b10 0
b10 =
14
b1 9
b1 G
b11 J
b10 I
1!
#150000
0!
#155000
b11110 $
b11110 M
b11110 /
b11110 @
b11110 0
b11110 =
13
b0 9
b0 G
04
b0 J
b11 I
1!
#160000
0!
#165000
17
03
b1 J
b1000000000000100 #
b100 <
b0 I
1!
#170000
0!
#175000
1.
b0 $
b0 M
b0 /
b0 @
b0 0
b0 =
b0 )
b0 O
b0 &
b0 L
b100 %
07
b10 J
b1000 +
b1000 A
b0 (
b0 N
b100 ,
b100 -
b1 I
b1000000000000100 ;
1!
#180000
0!
#185000
16
b11 J
b10 I
1!
#190000
0!
#195000
13
06
b0 J
b11 I
1!
#200000
0!
#205000
17
03
b1 J
bx #
b101 <
b0 I
1!
#210000
0!
#215000
x.
bx $
bx M
bx 0
bx =
bx /
bx @
bx )
bx O
bx *
bx ?
bx P
bx &
bx L
bx %
07
b10 J
bx +
bx A
bx (
bx N
bx '
bx K
bx ,
bx -
b1 I
bx ;
1!
#220000
0!
#225000
b11 J
b10 I
1!
#230000
0!
#235000
13
b0 J
b11 I
1!
#240000
0!
#245000
17
03
b1 J
b110 <
b0 I
1!
#250000
0!
#255000
07
b10 J
b1 I
1!
#260000
0!
#265000
b11 J
b10 I
1!
